{"uuid":"492930a0b8af012d312138ac6f7d89ab","tag":"main","pages":[{"questions":[{"uuid":"492b9670b8af012d312238ac6f7d89ab","wanted":"Was soll gemacht werden? ","multiple_answers":false,"label":"Was soll gemacht werden? ","answers":[{"uuid":"492cd9f0b8af012d312338ac6f7d89ab","label":"Internetseite erstellen","preselect":false,"input_field":false},{"uuid":"492daba0b8af012d312438ac6f7d89ab","label":"Internetseite aktualisieren","preselect":false,"input_field":false},{"uuid":"492e7d20b8af012d312538ac6f7d89ab","label":"Sonstiges","preselect":false,"input_field":true}]},{"uuid":"493ac900b8af012d312738ac6f7d89ab","wanted":"Was f\u00fcr ein Projekt wollen Sie in Auftrag geben? ","multiple_answers":false,"label":"Was f\u00fcr ein Projekt wollen Sie in Auftrag geben? ","answers":[{"uuid":"493df360b8af012d312938ac6f7d89ab","label":"Private Website","preselect":false,"input_field":false},{"uuid":"493f1fa0b8af012d312a38ac6f7d89ab","label":"Firmenwebsite","preselect":false,"input_field":false},{"uuid":"493cca50b8af012d312838ac6f7d89ab","label":"Onlineshop","preselect":false,"input_field":false},{"uuid":"494054a0b8af012d312b38ac6f7d89ab","label":"Sonstige:","preselect":false,"input_field":true},{"uuid":"49419000b8af012d312c38ac6f7d89ab","label":"Wei\u00df nicht","preselect":false,"input_field":false}]},{"uuid":"4944d640b8af012d312d38ac6f7d89ab","wanted":"Wer soll die Pflege der Seite \u00fcbernehmen?","multiple_answers":false,"label":"Wer soll die Pflege der Seite \u00fcbernehmen?","answers":[{"uuid":"49488150b8af012d312e38ac6f7d89ab","label":"Der Webdesigner soll die Seite pflegen","preselect":false,"input_field":false},{"uuid":"494b35f0b8af012d312f38ac6f7d89ab","label":"Eigenst\u00e4ndige Pflege der Seite ist vorgesehen","preselect":false,"input_field":false},{"uuid":"494dfa60b8af012d313038ac6f7d89ab","label":"Keine Pflege / Aktualisierung der Inhalte der Webseite n\u00f6tig","preselect":false,"input_field":false}]},{"uuid":"4956fbf0b8af012d313238ac6f7d89ab","wanted":"Haben Sie bereits eine Domain oder einen Server f\u00fcr die Seite?","multiple_answers":false,"label":"Haben Sie bereits eine Domain oder einen Server f\u00fcr die Seite?","answers":[{"uuid":"495d40a0b8af012d313338ac6f7d89ab","label":"Ja - Domain bereits vorhanden","preselect":false,"input_field":false},{"uuid":"49613660b8af012d313438ac6f7d89ab","label":"Ja - Server bereits vorhanden","preselect":false,"input_field":false},{"uuid":"49653530b8af012d313538ac6f7d89ab","label":"Ja - Domain und Server bereits vorhanden","preselect":false,"input_field":false},{"uuid":"49694780b8af012d313638ac6f7d89ab","label":"Nein - Noch nichts vorhanden","preselect":false,"input_field":false},{"uuid":"497b50a0b8af012d313738ac6f7d89ab","label":"Wei\u00df nicht","preselect":false,"input_field":false}]}]},{"questions":[{"uuid":"49841300b8af012d313838ac6f7d89ab","wanted":"Welche Aussage trifft am ehesten auf Ihr Unternehmen zu?","multiple_answers":false,"label":"Welche Aussage trifft am ehesten auf Ihr Unternehmen zu?","answers":[{"uuid":"498cca30b8af012d313938ac6f7d89ab","label":"(noch) Privatperson","preselect":false,"input_field":false},{"uuid":"499290d0b8af012d313a38ac6f7d89ab","label":"geplante Gr\u00fcndung in unbestimmter Zukunft","preselect":false,"input_field":false},{"uuid":"49abb7c0b8af012d313d38ac6f7d89ab","label":"Unternehmen ist j\u00fcnger als 6 Monate","preselect":false,"input_field":false},{"uuid":"499a86a0b8af012d313b38ac6f7d89ab","label":"Unternehmen ist \u00e4lter als 6 Monate","preselect":false,"input_field":false},{"uuid":"49b477e0b8af012d313e38ac6f7d89ab","label":"Sonstiges","preselect":false,"input_field":true}]},{"uuid":"49c3b6b0b8af012d313f38ac6f7d89ab","wanted":"Bis wann sollten die Arbeiten an Ihrer Webseite sp\u00e4testens abgeschlossen sein?","multiple_answers":false,"label":"Bis wann sollten die Arbeiten an Ihrer Webseite sp\u00e4testens abgeschlossen sein?","answers":[{"uuid":"49d3e340b8af012d314038ac6f7d89ab","label":"So schnell wie m\u00f6glich","preselect":false,"input_field":false},{"uuid":"49f0c330b8af012d314138ac6f7d89ab","label":"Innerhalb eines Monats","preselect":false,"input_field":false},{"uuid":"49fc3cd0b8af012d314238ac6f7d89ab","label":"In 1 bis 2 Monaten","preselect":false,"input_field":false},{"uuid":"4a07d990b8af012d314338ac6f7d89ab","label":"In 2 bis 3 Monaten","preselect":false,"input_field":false},{"uuid":"4a13ac10b8af012d314438ac6f7d89ab","label":"In 3 bis 6 Monaten","preselect":false,"input_field":false},{"uuid":"4a20d620b8af012d314538ac6f7d89ab","label":"In mehr als 6 Monaten","preselect":false,"input_field":false},{"uuid":"4a2bfa00b8af012d314638ac6f7d89ab","label":"Genaues Datum bekannt:","preselect":false,"input_field":true},{"uuid":"4a326290b8af012d314738ac6f7d89ab","label":"Wei\u00df noch nicht","preselect":false,"input_field":false}]}]}]}