{"uuid":"5a3e68b0b8af012d335238ac6f7d89ab","tag":"main","pages":[{"questions":[{"uuid":"5a41f150b8af012d335338ac6f7d89ab","wanted":"Wie viele Hostessen ben\u00f6tigen Sie?","multiple_answers":false,"label":"Wie viele Hostessen ben\u00f6tigen Sie?","answers":[{"uuid":"5a441190b8af012d335438ac6f7d89ab","label":"1","preselect":false,"input_field":false},{"uuid":"5a456ce0b8af012d335538ac6f7d89ab","label":"2","preselect":false,"input_field":false},{"uuid":"5a46c8b0b8af012d335638ac6f7d89ab","label":"3 oder mehr","preselect":false,"input_field":false},{"uuid":"5a482ce0b8af012d335738ac6f7d89ab","label":"Wei\u00df nicht","preselect":false,"input_field":false}]},{"uuid":"5a4ddaa0b8af012d335838ac6f7d89ab","wanted":"Welche Aufgabenbereiche sollen die Hostessen wahrnehmen? (Mehrfachauswahl m\u00f6glich)","multiple_answers":true,"label":"Welche Aufgabenbereiche sollen die Hostessen wahrnehmen? (Mehrfachauswahl m\u00f6glich)","answers":[{"uuid":"5a5142b0b8af012d335938ac6f7d89ab","label":"Empfang","preselect":false,"input_field":false},{"uuid":"5a532ed0b8af012d335a38ac6f7d89ab","label":"Fahrdienst","preselect":false,"input_field":false},{"uuid":"5a5525b0b8af012d335b38ac6f7d89ab","label":"Garderobe","preselect":false,"input_field":false},{"uuid":"5a572a30b8af012d335c38ac6f7d89ab","label":"Messestandbetreuung","preselect":false,"input_field":false},{"uuid":"5a593910b8af012d335d38ac6f7d89ab","label":"Produktberatung","preselect":false,"input_field":false},{"uuid":"5a5b58d0b8af012d335e38ac6f7d89ab","label":"Service / Verkostung","preselect":false,"input_field":false},{"uuid":"5a5d8560b8af012d335f38ac6f7d89ab","label":"Verkauf","preselect":false,"input_field":false},{"uuid":"5a5fc070b8af012d336038ac6f7d89ab","label":"Verteilung von Werbeartikeln","preselect":false,"input_field":false},{"uuid":"5a6269d0b8af012d336138ac6f7d89ab","label":"VIP-Betreuung","preselect":false,"input_field":false},{"uuid":"5a6532a0b8af012d336238ac6f7d89ab","label":"Sonstige:","preselect":false,"input_field":true},{"uuid":"5a6803e0b8af012d336338ac6f7d89ab","label":"Wei\u00df nicht","preselect":false,"input_field":false}]},{"uuid":"5a6ee9c0b8af012d336438ac6f7d89ab","wanted":"Sollen die Hostessen \u00fcber bestimmte Sprachkenntnisse verf\u00fcgen? (Mehrfachauswahl m\u00f6glich)","multiple_answers":true,"label":"Sollen die Hostessen \u00fcber bestimmte Sprachkenntnisse verf\u00fcgen? (Mehrfachauswahl m\u00f6glich)","answers":[{"uuid":"5a761890b8af012d336538ac6f7d89ab","label":"Englisch","preselect":false,"input_field":false},{"uuid":"5a7a4150b8af012d336638ac6f7d89ab","label":"Franz\u00f6sisch","preselect":false,"input_field":false},{"uuid":"5a8dad40b8af012d336738ac6f7d89ab","label":"Italienisch","preselect":false,"input_field":false},{"uuid":"5a923490b8af012d336838ac6f7d89ab","label":"Russisch","preselect":false,"input_field":false},{"uuid":"5a96b010b8af012d336938ac6f7d89ab","label":"Spanisch","preselect":false,"input_field":false},{"uuid":"5a9b3f90b8af012d336a38ac6f7d89ab","label":"Sonstige:","preselect":false,"input_field":true},{"uuid":"5a9ffde0b8af012d336b38ac6f7d89ab","label":"Wei\u00df nicht","preselect":false,"input_field":false}]},{"uuid":"5aa98cf0b8af012d336c38ac6f7d89ab","wanted":"F\u00fcr welche Art von Veranstaltung ben\u00f6tigen Sie Personal? ","multiple_answers":false,"label":"F\u00fcr welche Art von Veranstaltung ben\u00f6tigen Sie Personal? ","answers":[{"uuid":"5ab272b0b8af012d336d38ac6f7d89ab","label":"Event","preselect":false,"input_field":false},{"uuid":"5ab77d80b8af012d336e38ac6f7d89ab","label":"Messe","preselect":false,"input_field":false},{"uuid":"5abc93b0b8af012d336f38ac6f7d89ab","label":"Promotion","preselect":false,"input_field":false},{"uuid":"5ac1da90b8af012d337038ac6f7d89ab","label":"Sonstige:","preselect":false,"input_field":true},{"uuid":"5ac721c0b8af012d337138ac6f7d89ab","label":"Wei\u00df nicht","preselect":false,"input_field":false}]}]},{"questions":[{"uuid":"5ad0c1b0b8af012d337238ac6f7d89ab","wanted":"Welche  F\u00e4higkeiten und Voraussetzungen soll das Personal mitbringen? (Mehrfachauswahl m\u00f6glich)","multiple_answers":true,"label":"Welche  F\u00e4higkeiten und Voraussetzungen soll das Personal mitbringen? (Mehrfachauswahl m\u00f6glich)","answers":[{"uuid":"5adb68b0b8af012d337338ac6f7d89ab","label":"Barkeeper","preselect":false,"input_field":false},{"uuid":"5aef9170b8af012d337438ac6f7d89ab","label":"F\u00fchrerschein","preselect":false,"input_field":false},{"uuid":"5af6a4e0b8af012d337538ac6f7d89ab","label":"Kellnererfahrung","preselect":false,"input_field":false},{"uuid":"5afc81d0b8af012d337638ac6f7d89ab","label":"Kinderbetreuung","preselect":false,"input_field":false},{"uuid":"5b017dc0b8af012d337738ac6f7d89ab","label":"Moderation / Pr\u00e4sentation","preselect":false,"input_field":false},{"uuid":"5b069560b8af012d337838ac6f7d89ab","label":"Sonstige:","preselect":false,"input_field":true},{"uuid":"5b0b9e80b8af012d337938ac6f7d89ab","label":"Wei\u00df nicht - Bitte beraten Sie mich","preselect":false,"input_field":false},{"uuid":"5b10b830b8af012d337a38ac6f7d89ab","label":"Wei\u00df nicht","preselect":false,"input_field":false}]},{"uuid":"5b1987d0b8af012d337b38ac6f7d89ab","wanted":"Wann findet Ihre Veranstaltung statt?","multiple_answers":false,"label":"Wann findet Ihre Veranstaltung statt?","answers":[{"uuid":"5b230c80b8af012d337c38ac6f7d89ab","label":"So schnell wie m\u00f6glich","preselect":false,"input_field":false},{"uuid":"5b333450b8af012d337d38ac6f7d89ab","label":"Innerhalb eines Montas","preselect":false,"input_field":false},{"uuid":"5b3a0690b8af012d337e38ac6f7d89ab","label":"In 1 bis 2 Monaten","preselect":false,"input_field":false},{"uuid":"5b40cdf0b8af012d337f38ac6f7d89ab","label":"In 2 bis 3 Monaten","preselect":false,"input_field":false},{"uuid":"5b47aff0b8af012d338038ac6f7d89ab","label":"In mehr als 3 Monaten","preselect":false,"input_field":false},{"uuid":"5b4ebaa0b8af012d338138ac6f7d89ab","label":"Genaues Datum bekannt:","preselect":false,"input_field":true},{"uuid":"5b55b510b8af012d338238ac6f7d89ab","label":"Wei\u00df nicht","preselect":false,"input_field":false}]}]}]}