{"uuid":"93dc0480b8af012d3cad38ac6f7d89ab","tag":"main","pages":[{"questions":[{"label":"H\u00f6he des Gesch\u00e4ftswerts?","uuid":"93deff30b8af012d3cae38ac6f7d89ab","wanted":"H\u00f6he des Gesch\u00e4ftswerts?","multiple_answers":false,"answers":[{"label":"Unter 300.000 Euro","uuid":"93e0de30b8af012d3caf38ac6f7d89ab","preselect":false,"input_field":false},{"label":"300.000 bis 500.000 Euro","uuid":"93e21800b8af012d3cb038ac6f7d89ab","preselect":false,"input_field":false},{"label":"Wei\u00df nicht","uuid":"93e35620b8af012d3cb138ac6f7d89ab","preselect":false,"input_field":false},{"label":"Mehr als 500.000 Euro","uuid":"93e498f0b8af012d3cb238ac6f7d89ab","preselect":false,"input_field":false}]},{"label":"F\u00fcr welchen Rechtsbereich ben\u00f6tigen Sie den Notar?","uuid":"93e84f20b8af012d3cb338ac6f7d89ab","wanted":"F\u00fcr welchen Rechtsbereich ben\u00f6tigen Sie den Notar?","multiple_answers":false,"answers":[{"label":"Arbeitsrecht","uuid":"93eb2830b8af012d3cb438ac6f7d89ab","preselect":false,"input_field":false},{"label":"Unternehmensrecht","uuid":"93ecdf30b8af012d3cb538ac6f7d89ab","preselect":false,"input_field":false},{"label":"Andere:","uuid":"93ee9f50b8af012d3cb638ac6f7d89ab","preselect":false,"input_field":true},{"label":"Wei\u00df nicht","uuid":"93f06a20b8af012d3cb738ac6f7d89ab","preselect":false,"input_field":false}]},{"label":"In welcher Angelegenheit ben\u00f6tigen Sie einen Notar? (Mehrfachauswahl m\u00f6glich)","uuid":"93f529a0b8af012d3cb838ac6f7d89ab","wanted":"In welcher Angelegenheit ben\u00f6tigen Sie einen Notar? (Mehrfachauswahl m\u00f6glich)","multiple_answers":true,"answers":[{"label":"Durchf\u00fchrung von Gesellschaftsversammlungen","uuid":"93f940d0b8af012d3cb938ac6f7d89ab","preselect":false,"input_field":false},{"label":"\u00dcbertragung von Gesellschaftsanteilen","uuid":"93fba6e0b8af012d3cba38ac6f7d89ab","preselect":false,"input_field":false},{"label":"Unternehmenstransaktion","uuid":"93fe0e80b8af012d3cbb38ac6f7d89ab","preselect":false,"input_field":false},{"label":"Vertragsabschluss","uuid":"940085a0b8af012d3cbc38ac6f7d89ab","preselect":false,"input_field":false},{"label":"Andere:","uuid":"940e4470b8af012d3cbd38ac6f7d89ab","preselect":false,"input_field":false},{"label":"Wei\u00df nicht - Bitte beraten Sie mich","uuid":"9410e680b8af012d3cbe38ac6f7d89ab","preselect":false,"input_field":false},{"label":"Wei\u00df nicht","uuid":"941390d0b8af012d3cbf38ac6f7d89ab","preselect":false,"input_field":false}]},{"label":"Ab wann sollte der Notar Ihnen zur Verf\u00fcgung stehen?","uuid":"9419a0b0b8af012d3cc038ac6f7d89ab","wanted":"Ab wann sollte der Notar Ihnen zur Verf\u00fcgung stehen?","multiple_answers":false,"answers":[{"label":"So schnell wie m\u00f6glich","uuid":"941f7c20b8af012d3cc138ac6f7d89ab","preselect":false,"input_field":false},{"label":"Innerhalb eines Monats","uuid":"94233760b8af012d3cc238ac6f7d89ab","preselect":false,"input_field":false},{"label":"In 1 bis 2 Monaten","uuid":"9426fd30b8af012d3cc338ac6f7d89ab","preselect":false,"input_field":false},{"label":"In 2 bis 3 Monaten","uuid":"942ad270b8af012d3cc438ac6f7d89ab","preselect":false,"input_field":false},{"label":"In mehr als 3 Monaten","uuid":"942ec1e0b8af012d3cc538ac6f7d89ab","preselect":false,"input_field":false},{"label":"Genaues Datum bekannt:","uuid":"9432bc70b8af012d3cc638ac6f7d89ab","preselect":false,"input_field":true},{"label":"Wei\u00df nicht","uuid":"9436cc30b8af012d3cc738ac6f7d89ab","preselect":false,"input_field":false}]}]}]}