{"uuid":"a8eabbb0b8af012d3f7138ac6f7d89ab","tag":"main","pages":[{"questions":[{"uuid":"a8ed3580b8af012d3f7238ac6f7d89ab","wanted":"Um wie viele G\u00e4ste handelt es sich?","multiple_answers":false,"label":"Um wie viele G\u00e4ste handelt es sich?","answers":[{"uuid":"a8ee8da0b8af012d3f7338ac6f7d89ab","label":"Unter 50","preselect":false,"input_field":false},{"uuid":"a8ef6fe0b8af012d3f7438ac6f7d89ab","label":"50 bis 100","preselect":false,"input_field":false},{"uuid":"a8f051c0b8af012d3f7538ac6f7d89ab","label":"100 bis 250","preselect":false,"input_field":false},{"uuid":"a8f137c0b8af012d3f7638ac6f7d89ab","label":"Mehr als 250","preselect":false,"input_field":false},{"uuid":"a8f21f00b8af012d3f7738ac6f7d89ab","label":"Wei\u00df nicht","preselect":false,"input_field":false}]},{"uuid":"a8f51fc0b8af012d3f7838ac6f7d89ab","wanted":"Um welche Art von Hochzeit handelt es sich? ","multiple_answers":false,"label":"Um welche Art von Hochzeit handelt es sich? ","answers":[{"uuid":"a8f73950b8af012d3f7938ac6f7d89ab","label":"Standesamtliche Hochzeit","preselect":false,"input_field":false},{"uuid":"a8f87b80b8af012d3f7a38ac6f7d89ab","label":"Kirchliche Hochzeit","preselect":false,"input_field":false},{"uuid":"a8f9cac0b8af012d3f7b38ac6f7d89ab","label":"Standesamtlich und kirchliche Hochzeit","preselect":false,"input_field":false},{"uuid":"a8fc9bc0b8af012d3f7c38ac6f7d89ab","label":"Trauung mit einem Freien Theologen","preselect":false,"input_field":false},{"uuid":"a8ff8340b8af012d3f7d38ac6f7d89ab","label":"Wei\u00df nicht","preselect":false,"input_field":false}]},{"uuid":"a906c870b8af012d3f7e38ac6f7d89ab","wanted":"Was soll au\u00dferhalb der eigentlichen Hochzeit vom Hochzeitsplaner organisiert werden? (Mehrfachauswahl m\u00f6glich)","multiple_answers":true,"label":"Was soll au\u00dferhalb der eigentlichen Hochzeit vom Hochzeitsplaner organisiert werden? (Mehrfachauswahl m\u00f6glich)","answers":[{"uuid":"a90d8180b8af012d3f7f38ac6f7d89ab","label":"Flitterwochen","preselect":false,"input_field":false},{"uuid":"a9119b80b8af012d3f8038ac6f7d89ab","label":"Polterabend","preselect":false,"input_field":false},{"uuid":"a9265a70b8af012d3f8138ac6f7d89ab","label":"Tanzschule","preselect":false,"input_field":false},{"uuid":"a92aaae0b8af012d3f8238ac6f7d89ab","label":"Andere:","preselect":false,"input_field":true},{"uuid":"a92f0e20b8af012d3f8338ac6f7d89ab","label":"Wei\u00df nicht","preselect":false,"input_field":false}]},{"uuid":"a9388180b8af012d3f8438ac6f7d89ab","wanted":"Ist bereits bekannt, wo die Feierlichkeiten stattfinden sollen bzw. gibt es einen konkreten Wunsch?","multiple_answers":false,"label":"Ist bereits bekannt, wo die Feierlichkeiten stattfinden sollen bzw. gibt es einen konkreten Wunsch?","answers":[{"uuid":"a941ff00b8af012d3f8538ac6f7d89ab","label":"Ja","preselect":false,"input_field":false},{"uuid":"a9473d30b8af012d3f8638ac6f7d89ab","label":"Nein, Aufgabe des Hochzeitsplaners","preselect":false,"input_field":false},{"uuid":"a94a0ba0b8af012d3f8738ac6f7d89ab","label":"Nein","preselect":false,"input_field":false},{"uuid":"a94cebb0b8af012d3f8838ac6f7d89ab","label":"Wei\u00df nicht - Bitte beraten Sie mich","preselect":false,"input_field":false},{"uuid":"a94fd080b8af012d3f8938ac6f7d89ab","label":"Wei\u00df nicht","preselect":false,"input_field":false}]},{"uuid":"a955abb0b8af012d3f8a38ac6f7d89ab","wanted":"Wann ist Ihre Hochzeit geplant?","multiple_answers":false,"label":"Wann ist Ihre Hochzeit geplant?","answers":[{"uuid":"a95b6a20b8af012d3f8b38ac6f7d89ab","label":"So schnell wie m\u00f6glich","preselect":false,"input_field":false},{"uuid":"a95f3940b8af012d3f8c38ac6f7d89ab","label":"Innerhalb der n\u00e4chsten 2 Monate","preselect":false,"input_field":false},{"uuid":"a96318e0b8af012d3f8d38ac6f7d89ab","label":"In 2 bis 6 Monaten","preselect":false,"input_field":false},{"uuid":"a96ff330b8af012d3f8e38ac6f7d89ab","label":"In 6 bis 12 Monaten","preselect":false,"input_field":false},{"uuid":"a9740b50b8af012d3f8f38ac6f7d89ab","label":"In mehr als einem Jahr","preselect":false,"input_field":false},{"uuid":"a9782940b8af012d3f9038ac6f7d89ab","label":"Genaues Datum bekannt:","preselect":false,"input_field":true},{"uuid":"a97c6700b8af012d3f9138ac6f7d89ab","label":"Wei\u00df nicht","preselect":false,"input_field":false}]}]},{"questions":[{"uuid":"a983df50b8af012d3f9238ac6f7d89ab","wanted":"W\u00fcnschen Sie einen bestimmten Ort f\u00fcr die Hochzeitsfeierlichkeiten? (Mehrfachauswahl m\u00f6glich)","multiple_answers":true,"label":"W\u00fcnschen Sie einen bestimmten Ort f\u00fcr die Hochzeitsfeierlichkeiten? (Mehrfachauswahl m\u00f6glich)","answers":[{"uuid":"a98bbef0b8af012d3f9338ac6f7d89ab","label":"Ballsaal","preselect":false,"input_field":false},{"uuid":"a9911980b8af012d3f9438ac6f7d89ab","label":"Garten","preselect":false,"input_field":false},{"uuid":"a999e190b8af012d3f9538ac6f7d89ab","label":"Hotel","preselect":false,"input_field":false},{"uuid":"a9a50150b8af012d3f9638ac6f7d89ab","label":"Scheune","preselect":false,"input_field":false},{"uuid":"a9c07eb0b8af012d3f9738ac6f7d89ab","label":"Schiff","preselect":false,"input_field":false},{"uuid":"a9cc0fd0b8af012d3f9838ac6f7d89ab","label":"Schloss","preselect":false,"input_field":false},{"uuid":"a9d7eb20b8af012d3f9938ac6f7d89ab","label":"Strand","preselect":false,"input_field":false},{"uuid":"a9e20f30b8af012d3f9a38ac6f7d89ab","label":"Villa","preselect":false,"input_field":false},{"uuid":"a9e81570b8af012d3f9b38ac6f7d89ab","label":"Andere:","preselect":false,"input_field":false},{"uuid":"a9ee32a0b8af012d3f9c38ac6f7d89ab","label":"Wei\u00df nicht - Bitte beraten Sie mich","preselect":false,"input_field":false},{"uuid":"a9f44fa0b8af012d3f9d38ac6f7d89ab","label":"Wei\u00df nicht","preselect":false,"input_field":false}]},{"uuid":"a9fe4e10b8af012d3f9e38ac6f7d89ab","wanted":"Wo liegen die Aufgabenbereiche des Hochzeitsplaners? (Mehrfachauswahl m\u00f6glich)","multiple_answers":true,"label":"Wo liegen die Aufgabenbereiche des Hochzeitsplaners? (Mehrfachauswahl m\u00f6glich)","answers":[{"uuid":"aa124480b8af012d3f9f38ac6f7d89ab","label":"Brautkleid / Br\u00e4utigamssakko","preselect":false,"input_field":false},{"uuid":"aa1a2cb0b8af012d3fa038ac6f7d89ab","label":"Catering (inkl. Hochzeitstorte)","preselect":false,"input_field":false},{"uuid":"aa220f10b8af012d3fa138ac6f7d89ab","label":"Dekoration","preselect":false,"input_field":false},{"uuid":"aa29fa30b8af012d3fa238ac6f7d89ab","label":"Fahrzeuge","preselect":false,"input_field":false},{"uuid":"aa31f680b8af012d3fa338ac6f7d89ab","label":"Fotograf","preselect":false,"input_field":false},{"uuid":"aa3a2120b8af012d3fa438ac6f7d89ab","label":"Kameramann","preselect":false,"input_field":false},{"uuid":"aa424650b8af012d3fa538ac6f7d89ab","label":"Kinderbetreuung","preselect":false,"input_field":false},{"uuid":"aa53ea40b8af012d3fa638ac6f7d89ab","label":"Kleidung f\u00fcr Blumenkinder","preselect":false,"input_field":false},{"uuid":"aa5c6380b8af012d3fa738ac6f7d89ab","label":"Musik und Unterhaltung","preselect":false,"input_field":false},{"uuid":"aa64f600b8af012d3fa838ac6f7d89ab","label":"\u00d6rtlichkeit","preselect":false,"input_field":false},{"uuid":"aa6dbc30b8af012d3fa938ac6f7d89ab","label":"Personal","preselect":false,"input_field":false},{"uuid":"aa767730b8af012d3faa38ac6f7d89ab","label":"Trauringe","preselect":false,"input_field":false},{"uuid":"aa7f4c80b8af012d3fab38ac6f7d89ab","label":"Weitere Angabe:","preselect":false,"input_field":true},{"uuid":"aa8822f0b8af012d3fac38ac6f7d89ab","label":"Wei\u00df nicht","preselect":false,"input_field":false}]}]}]}